ai_voice_sdk/__init__.py
ai_voice_sdk/config.py
ai_voice_sdk/converter.py
ai_voice_sdk/enums.py
ai_voice_sdk/textedit.py
ai_voice_sdk/units.py
ai_voice_sdk_standard-0.0.2.dist-info/LICENSE
ai_voice_sdk_standard-0.0.2.dist-info/METADATA
ai_voice_sdk_standard-0.0.2.dist-info/WHEEL
ai_voice_sdk_standard-0.0.2.dist-info/top_level.txt
ai_voice_sdk_standard-0.0.2.dist-info/RECORD
