Metadata-Version: 2.1
Name: ai-voice-sdk-standard
Version: 0.0.2
Summary: Aten AI Voice SDK Standard
Home-page: https://github.com/ATEN-International/ai-voice-sdk-python-standard
Author: ATEN-International
Author-email: rdmaten@aten.com.tw
Classifier: Programming Language :: Python :: 3
Classifier: License :: OSI Approved :: MIT License
Classifier: Operating System :: OS Independent
Requires-Python: >=3.7
License-File: LICENSE
Requires-Dist: requests
Requires-Dist: wave
Requires-Dist: simpleaudio
